LICENSE
README.md
setup.py
spb_cli/__init__.py
spb_cli/__main__.py
spb_cli/config.json
spb_cli/labels/__init__.py
spb_cli/labels/base_service.py
spb_cli/labels/exceptions.py
spb_cli/labels/creates/__init__.py
spb_cli/labels/describes/__init__.py
spb_cli/labels/describes/projects.py
spb_cli/labels/downloads/__init__.py
spb_cli/labels/downloads/downloads.py
spb_cli/labels/uploads/__init__.py
spb_cli/labels/uploads/upload_data.py
spb_cli/labels/uploads/upload_labels.py
spb_cli/labels/utils/__init__.py
superb_ai_cli.egg-info/PKG-INFO
superb_ai_cli.egg-info/SOURCES.txt
superb_ai_cli.egg-info/dependency_links.txt
superb_ai_cli.egg-info/entry_points.txt
superb_ai_cli.egg-info/not-zip-safe
superb_ai_cli.egg-info/requires.txt
superb_ai_cli.egg-info/top_level.txt