Metadata-Version: 2.1
Name: superb-ai-cli
Version: 0.1.2
Summary: Superb Platform CLI
Home-page: https://github.com/Superb-AI-Suite/superb-ai-cli
Author: Superb AI Dev Team
Author-email: support@superb-ai.com
License: MIT
Classifier: Development Status :: 1 - Planning
Classifier: Intended Audience :: Developers
Classifier: Topic :: Software Development :: Libraries
Classifier: License :: OSI Approved :: MIT License
Classifier: Programming Language :: Python :: 3.7
Classifier: Programming Language :: Python :: 3.8
Classifier: Programming Language :: Python :: 3.9
Classifier: Programming Language :: Python :: 3.10
Classifier: Programming Language :: Python :: 3.11
Classifier: Programming Language :: Python :: 3.12
License-File: LICENSE
